<?xml version="1.0" encoding="UTF-8"?>
<objects serializationModel="Studio.02.02.00">
	<object class="AudioFile" id="{f26314e7-9481-43ee-9a2c-6c55fcfd1a15}">
		<property name="assetPath">
			<value>Sampling/loop-black-box-exciting-bass-loop-130bpm-13888.mp3</value>
		</property>
		<property name="isStreaming">
			<value>true</value>
		</property>
		<property name="frequencyInKHz">
			<value>44.0999985</value>
		</property>
		<property name="channelCount">
			<value>2</value>
		</property>
		<property name="length">
			<value>74.501224489795916</value>
		</property>
		<relationship name="masterAssetFolder">
			<destination>{887a0d66-1d05-47b1-b2df-f1d0fd7bd36d}</destination>
		</relationship>
	</object>
</objects>
